concept_erasure/__init__.py
concept_erasure/caching.py
concept_erasure/concept_scrubber.py
concept_erasure/groupby.py
concept_erasure/leace.py
concept_erasure/optimal_transport.py
concept_erasure/oracle.py
concept_erasure/quadratic.py
concept_erasure/shrinkage.py
concept_erasure/utils.py
concept_erasure/scrubbing/__init__.py
concept_erasure/scrubbing/auto.py
concept_erasure/scrubbing/llama.py
concept_erasure/scrubbing/neox.py
concept_erasure/scrubbing/random_scrub.py
concept_erasure-0.2.4.dist-info/LICENSE
concept_erasure-0.2.4.dist-info/METADATA
concept_erasure-0.2.4.dist-info/WHEEL
concept_erasure-0.2.4.dist-info/entry_points.txt
concept_erasure-0.2.4.dist-info/top_level.txt
concept_erasure-0.2.4.dist-info/RECORD
