Metadata-Version: 2.1
Name: concept-erasure
Version: 0.2.4
Summary: Erasing concepts from neural representations with provable guarantees
License: MIT License
Keywords: fairness,interpretability,explainable-ai
Requires-Python: >=3.10
License-File: LICENSE
Requires-Dist: torch
Provides-Extra: dev
Requires-Dist: numpy ; extra == 'dev'
Requires-Dist: pre-commit ; extra == 'dev'
Requires-Dist: pytest ; extra == 'dev'
Requires-Dist: pyright ; extra == 'dev'
Requires-Dist: scikit-learn ; extra == 'dev'
Requires-Dist: datasets ; extra == 'dev'
Requires-Dist: transformers >=4.0.0 ; extra == 'dev'
